dupechecker/__init__.py
dupechecker/dupechecker.py
dupechecker-1.0.1.dist-info/METADATA
dupechecker-1.0.1.dist-info/WHEEL
dupechecker-1.0.1.dist-info/entry_points.txt
dupechecker-1.0.1.dist-info/licenses/LICENSE.txt
dupechecker-1.0.1.dist-info/RECORD
