Metadata-Version: 2.1
Name: dupechecker
Version: 1.0.1
Summary: Check for and delete duplicate files from the command line.
Project-URL: Homepage, https://github.com/matt-manes/dupechecker
Project-URL: Documentation, https://github.com/matt-manes/dupechecker/tree/main/docs
Project-URL: Source code, https://github.com/matt-manes/dupechecker/tree/main/src/dupechecker
Author-email: Matt Manes <mattmanes@pm.me>
License-File: LICENSE.txt
Keywords: cli,filecmp,filesystem
Classifier: License :: OSI Approved :: MIT License
Classifier: Operating System :: OS Independent
Classifier: Programming Language :: Python :: 3
Requires-Python: >=3.10
Requires-Dist: griddle
Requires-Dist: noiftimer
Requires-Dist: pathier
Requires-Dist: printbuddies
Requires-Dist: pytest
Requires-Dist: younotyou
